sc_surelog-1.84.1.dist-info/RECORD
sc_surelog-1.84.1.dist-info/LICENSE
sc_surelog-1.84.1.dist-info/WHEEL
sc_surelog-1.84.1.dist-info/top_level.txt
sc_surelog-1.84.1.dist-info/METADATA
surelog/__init__.py
surelog/bin/README.md
surelog/bin/surelog
