Metadata-Version: 2.1
Name: sc-surelog
Version: 1.84.1
Summary: Precompiled binary for surelog.
Home-page: https://github.com/siliconcompiler/sc-surelog
Author: ZeroASIC
Author-email: gadfort@zeroasic.com
License: Apache License 2.0
Project-URL: Source Code, https://github.com/siliconcompiler/sc-surelog
Project-URL: Bug Tracker, https://github.com/siliconcompiler/sc-surelog/issues
Requires-Python: >=3.8
License-File: LICENSE
Provides-Extra: test
Requires-Dist: pytest==7.1.0; extra == "test"
Requires-Dist: flake8==7.0.0; extra == "test"
